streamlit_slice_select/__init__.py
streamlit_slice_select/frontend/dist/bootstrap.min.css
streamlit_slice_select/frontend/dist/index.html
streamlit_slice_select/frontend/dist/slicer.js
streamlit_slice_select/frontend/dist/slicer.js.LICENSE.txt
streamlit_slice_select/frontend/dist/style.css
streamlit_slice_select-0.1.2.dist-info/LICENSE.txt
streamlit_slice_select-0.1.2.dist-info/METADATA
streamlit_slice_select-0.1.2.dist-info/WHEEL
streamlit_slice_select-0.1.2.dist-info/top_level.txt
streamlit_slice_select-0.1.2.dist-info/RECORD
