Metadata-Version: 2.1
Name: streamlit-slice-select
Version: 0.1.2
Summary: A like Excel-slicer input widget for Streamlit
Author-email: Jaime Lopez <jaime.lopez@datainquiry.dev>
License: Apache License
License-File: LICENSE.txt
Requires-Dist: streamlit
Provides-Extra: dev
Requires-Dist: mypy ; extra == 'dev'
Requires-Dist: pylint ; extra == 'dev'
Requires-Dist: pytest ; extra == 'dev'
Requires-Dist: build ; extra == 'dev'
